[["Are there any foreign objects?", ["no"], [], {"answer_type": "single_choice", "options": ["yes", "no"], "path": "foreign objects_objects"}], ["Are there any signs in the lung?", ["yes"], [], {"answer_type": "single_choice", "options": ["yes", "no"], "path": "lung_signs"}], ["Is there a airspace disease in the lung?", ["no"], [["Are there any signs in the lung?", ["yes"]]], {"answer_type": "single_choice", "options": ["yes", "no"], "path": "lung_signs_airspace disease"}], ["Is there an consolidation in the lung?", ["no"], [["Are there any signs in the lung?", ["yes"]]], {"answer_type": "single_choice", "options": ["yes", "no"], "path": "lung_signs_consolidation"}], ["Is there an deformity in the lung?", ["no"], [["Are there any signs in the lung?", ["yes"]]], {"answer_type": "single_choice", "options": ["yes", "no"], "path": "lung_signs_deformity"}], ["Is there an density in the lung?", ["no"], [["Are there any signs in the lung?", ["yes"]]], {"answer_type": "single_choice", "options": ["yes", "no"], "path": "lung_signs_density"}], ["Is there an lucency in the lung?", ["no"], [["Are there any signs in the lung?", ["yes"]]], {"answer_type": "single_choice", "options": ["yes", "no"], "path": "lung_signs_lucency"}], ["Is there an markings in the lung?", ["no"], [["Are there any signs in the lung?", ["yes"]]], {"answer_type": "single_choice", "options": ["yes", "no"], "path": "lung_signs_markings"}], ["Is there an nipple shadow in the lung?", ["no"], [["Are there any signs in the lung?", ["yes"]]], {"answer_type": "single_choice", "options": ["yes", "no"], "path": "lung_signs_nipple shadow"}], ["Is there a opacity in the lung?", ["yes"], [["Are there any signs in the lung?", ["yes"]]], {"answer_type": "single_choice", "options": ["yes", "no"], "path": "lung_signs_opacity"}], ["In which part of the body?", ["right lower lobe", "right upper lobe", "middle lobe"], [["Are there any signs in the lung?", ["yes"]], ["Is there a opacity in the lung?", ["yes"]]], {"answer_type": "multi_choice", "options": ["apex", "interstitial", "left costophrenic angle", "left hilum", "left interstitial", "left lower lobe", "left upper lobe", "middle lobe", "pulmonary alveoli", "right costophrenic angle", "right hilum", "right interstitial", "right lower lobe", "right upper lobe"], "path": "lung_signs_opacity_body_region"}], ["What are the attributes?", ["no selection"], [["Are there any signs in the lung?", ["yes"]], ["Is there a opacity in the lung?", ["yes"]], ["In which part of the body?", ["right lower lobe", "right upper lobe", "middle lobe"]]], {"answer_type": "multi_choice", "options": ["diffuse", "focal", "irregular", "large", "multiple", "no selection", "patchy", "prominent", "reticular", "round", "scattered", "small", "streaky"], "path": "lung_signs_opacity_attributes"}], ["What is the degree?", ["no selection"], [["Are there any signs in the lung?", ["yes"]], ["Is there a opacity in the lung?", ["yes"]], ["In which part of the body?", ["right lower lobe", "right upper lobe", "middle lobe"]], ["What are the attributes?", ["no selection"]]], {"answer_type": "multi_choice", "options": ["abnormal", "chronic", "mild", "no selection", "severe"], "path": "lung_signs_opacity_degree"}], ["Is there another opacity in the lung?", ["no"], [["Are there any signs in the lung?", ["yes"]], ["Is there a opacity in the lung?", ["yes"]], ["In which part of the body?", ["right lower lobe", "right upper lobe", "middle lobe"]], ["What are the attributes?", ["no selection"]], ["What is the degree?", ["no selection"]]], {"answer_type": "single_choice", "options": ["yes", "no"], "path": "lung_signs_opacity"}], ["Is there an thickening in the lung?", ["no"], [["Are there any signs in the lung?", ["yes"]]], {"answer_type": "single_choice", "options": ["yes", "no"], "path": "lung_signs_thickening"}], ["Is there an volume loss in the lung?", ["no"], [["Are there any signs in the lung?", ["yes"]]], {"answer_type": "single_choice", "options": ["yes", "no"], "path": "lung_signs_volume loss"}], ["Is there an pneumonectomy in the lung?", ["no"], [["Are there any signs in the lung?", ["yes"]]], {"answer_type": "single_choice", "options": ["yes", "no"], "path": "lung_signs_pneumonectomy"}], ["Is there anything abnormal in the lung?", ["yes"], [], {"answer_type": "single_choice", "options": ["yes", "no"], "path": "lung_body_regions"}], ["Is there anything abnormal in the whole lung?", ["yes"], [["Is there anything abnormal in the lung?", ["yes"]]], {"answer_type": "single_choice", "options": ["yes", "no"], "path": "lung_body_regions"}], ["In which area?", ["unspecified"], [["Is there anything abnormal in the lung?", ["yes"]], ["Is there anything abnormal in the whole lung?", ["yes"]]], {"answer_type": "multi_choice", "options": ["bilateral", "interstitial", "left", "right", "unspecified"], "path": "lung_body_regions_localization"}], ["What are the attributes?", ["no selection"], [["Is there anything abnormal in the lung?", ["yes"]], ["Is there anything abnormal in the whole lung?", ["yes"]], ["In which area?", ["unspecified"]]], {"answer_type": "multi_choice", "options": ["diffuse", "no selection", "obscured", "prominent"], "path": "lung_body_regions_attributes"}], ["What is the degree?", ["hypoinflation"], [["Is there anything abnormal in the lung?", ["yes"]], ["Is there anything abnormal in the whole lung?", ["yes"]], ["In which area?", ["unspecified"]], ["What are the attributes?", ["no selection"]]], {"answer_type": "multi_choice", "options": ["abnormal", "hyperdistention", "hypoinflation", "mild", "moderate", "no selection", "severe"], "path": "lung_body_regions_degree"}], ["Is there anything else abnormal in the whole lung?", ["no"], [["Is there anything abnormal in the lung?", ["yes"]], ["Is there anything abnormal in the whole lung?", ["yes"]], ["In which area?", ["unspecified"]], ["What are the attributes?", ["no selection"]], ["What is the degree?", ["hypoinflation"]]], {"answer_type": "single_choice", "options": ["yes", "no"], "path": "lung_body_regions"}], ["Is there anything abnormal in the diaphragm?", ["no"], [["Is there anything abnormal in the lung?", ["yes"]]], {"answer_type": "single_choice", "options": ["yes", "no"], "path": "lung_body_regions_diaphragm"}], ["Is there anything abnormal in the costophrenic angle?", ["no"], [["Is there anything abnormal in the lung?", ["yes"]]], {"answer_type": "single_choice", "options": ["yes", "no"], "path": "lung_body_regions_costophrenic angle"}], ["Is there anything abnormal in the hilum?", ["no"], [["Is there anything abnormal in the lung?", ["yes"]]], {"answer_type": "single_choice", "options": ["yes", "no"], "path": "lung_body_regions_hilum"}], ["Is there anything abnormal in the apex?", ["no"], [["Is there anything abnormal in the lung?", ["yes"]]], {"answer_type": "single_choice", "options": ["yes", "no"], "path": "lung_body_regions_apex"}], ["Is there anything abnormal in the azygos lobe?", ["no"], [["Is there anything abnormal in the lung?", ["yes"]]], {"answer_type": "single_choice", "options": ["yes", "no"], "path": "lung_body_regions_azygos lobe"}], ["Is there anything abnormal in the blood vessels?", ["no"], [["Is there anything abnormal in the lung?", ["yes"]]], {"answer_type": "single_choice", "options": ["yes", "no"], "path": "lung_body_regions_blood vessels"}], ["Are there any diseases in the lung?", ["no"], [], {"answer_type": "single_choice", "options": ["yes", "no"], "path": "lung_diseases"}], ["Are there any signs in the pleura?", ["no"], [], {"answer_type": "single_choice", "options": ["yes", "no"], "path": "pleura_signs"}], ["Is there anything abnormal in the pleura?", ["no"], [], {"answer_type": "single_choice", "options": ["yes", "no"], "path": "pleura_body_regions"}], ["Are there any diseases in the pleura?", ["no"], [], {"answer_type": "single_choice", "options": ["yes", "no"], "path": "pleura_diseases"}], ["Are there any signs in the trachea?", ["no"], [], {"answer_type": "single_choice", "options": ["yes", "no"], "path": "trachea_signs"}], ["Is there anything abnormal in the trachea?", ["no"], [], {"answer_type": "single_choice", "options": ["yes", "no"], "path": "trachea_body_regions"}], ["Are there any diseases in the trachea?", ["no"], [], {"answer_type": "single_choice", "options": ["yes", "no"], "path": "trachea_diseases"}], ["Are there any signs in the cardiovascular system?", ["no"], [], {"answer_type": "single_choice", "options": ["yes", "no"], "path": "cardiovascular system_signs"}], ["Is there anything abnormal in the cardiovascular system?", ["no"], [], {"answer_type": "single_choice", "options": ["yes", "no"], "path": "cardiovascular system_body_regions"}], ["Are there any diseases in the cardiovascular system?", ["no"], [], {"answer_type": "single_choice", "options": ["yes", "no"], "path": "cardiovascular system_diseases"}], ["Are there any signs in the skeletal system?", ["no"], [], {"answer_type": "single_choice", "options": ["yes", "no"], "path": "skeletal system_signs"}], ["Is there anything abnormal in the skeletal system?", ["no"], [], {"answer_type": "single_choice", "options": ["yes", "no"], "path": "skeletal system_body_regions"}], ["Are there any diseases in the skeletal system?", ["no"], [], {"answer_type": "single_choice", "options": ["yes", "no"], "path": "skeletal system_diseases"}], ["Are there any signs in the breast?", ["no"], [], {"answer_type": "single_choice", "options": ["yes", "no"], "path": "breast_signs"}], ["Are there any diseases in the breast?", ["no"], [], {"answer_type": "single_choice", "options": ["yes", "no"], "path": "breast_diseases"}], ["Are there any signs in the abdomen?", ["no"], [], {"answer_type": "single_choice", "options": ["yes", "no"], "path": "abdomen_signs"}], ["Is there anything abnormal in the abdomen?", ["no"], [], {"answer_type": "single_choice", "options": ["yes", "no"], "path": "abdomen_infos"}], ["Are there any diseases in the abdomen?", ["no"], [], {"answer_type": "single_choice", "options": ["yes", "no"], "path": "abdomen_diseases"}], ["Are there any signs in the thorax?", ["no"], [], {"answer_type": "single_choice", "options": ["yes", "no"], "path": "thorax_signs"}], ["Are there any diseases in the thorax?", ["no"], [], {"answer_type": "single_choice", "options": ["yes", "no"], "path": "thorax_diseases"}], ["Are there any signs in the mediastinum?", ["no"], [], {"answer_type": "single_choice", "options": ["yes", "no"], "path": "mediastinum_signs"}], ["Is there anything abnormal in the mediastinum?", ["no"], [], {"answer_type": "single_choice", "options": ["yes", "no"], "path": "mediastinum_infos"}], ["Are there any diseases in the mediastinum?", ["no"], [], {"answer_type": "single_choice", "options": ["yes", "no"], "path": "mediastinum_diseases"}], ["Is there anything abnormal in the lymph nodes?", ["no"], [], {"answer_type": "single_choice", "options": ["yes", "no"], "path": "lymph nodes_infos"}], ["Are there any diseases in the lymph nodes?", ["no"], [], {"answer_type": "single_choice", "options": ["yes", "no"], "path": "lymph nodes_diseases"}]]